finances/__init__.py
finances/admin.py
finances/apps.py
finances/forms.py
finances/models.py
finances/tests.py
finances/urls.py
finances/views.py
finances/workspace.py
finances/helpers/__init__.py
finances/helpers/reports.py
finances/helpers/upload_transactions.py
finances/migrations/0001_initial.py
finances/migrations/0002_auto_20190617_2005.py
finances/migrations/0003_auto_20190617_2027.py
finances/migrations/0004_auto_20190617_2048.py
finances/migrations/0005_auto_20190617_2135.py
finances/migrations/0006_auto_20190623_1317.py
finances/migrations/0007_paymentmethod.py
finances/migrations/0008_auto_20190629_1306.py
finances/migrations/0009_auto_20190629_1400.py
finances/migrations/0010_transaction_created.py
finances/migrations/__init__.py
finances/static/finances/main.css
finances/templates/finances/add_budget_categories.html
finances/templates/finances/add_payment_methods.html
finances/templates/finances/add_transactions.html
finances/templates/finances/historic_transactions.html
finances/templates/finances/index.html
finances/templates/finances/layout.html
finances/templates/finances/reports.html
finances/templates/finances/upload_transactions.html
finances/templatetags/__init__.py
finances/templatetags/finances_tags.py
django_personal_finances-0.4.dist-info/LICENSE
django_personal_finances-0.4.dist-info/METADATA
django_personal_finances-0.4.dist-info/WHEEL
django_personal_finances-0.4.dist-info/top_level.txt
django_personal_finances-0.4.dist-info/RECORD
