Metadata-Version: 2.1
Name: django-personal-finances
Version: 0.4
Summary: A Django app to track personal finances
Home-page: UNKNOWN
Author: Wade Roberts
Author-email: waderoberts123@gmail.com
License: MIT
Platform: UNKNOWN
Classifier: Environment :: Web Environment
Classifier: Framework :: Django :: 3.0
Classifier: Programming Language :: Python :: 3.7
Requires-Dist: Django
